doc/README-API.md
doc/README-BUILDING.md
doc/README-CLI-AUTH.md
doc/README-CLI.md
doc/README-DEVELOPERS.md
doc/README-INSTALL.md
doc/README-LDAP-DOCKER.md
doc/README-QUICKSTART.md
doc/README-TESTING.md
doc/README-UPGRADE-PYTHON.md
doc/TROUBLESHOOTING-GUIDE.md
py_fortress-0.1.7.data/data/conf/py-fortress-cfg.json.sample
rbac/__init__.py
rbac/access.py
rbac/admin.py
rbac/review.py
rbac/cli/__init__.py
rbac/cli/cli.py
rbac/cli/cli_test_auth.py
rbac/cli/utils.py
rbac/ldap/__init__.py
rbac/ldap/daoex.py
rbac/ldap/ditdao.py
rbac/ldap/ldaphelper.py
rbac/ldap/permdao.py
rbac/ldap/roledao.py
rbac/ldap/userdao.py
rbac/model/__init__.py
rbac/model/constraint.py
rbac/model/perm.py
rbac/model/perm_object.py
rbac/model/role.py
rbac/model/session.py
rbac/model/user.py
rbac/tests/__init__.py
rbac/tests/perm_test_data.py
rbac/tests/role_test_data.py
rbac/tests/test_access.py
rbac/tests/test_admin.py
rbac/tests/test_constraints.py
rbac/tests/test_dit_dao.py
rbac/tests/test_ldap_daos.py
rbac/tests/test_review.py
rbac/tests/test_samples.py
rbac/tests/user_test_data.py
rbac/util/__init__.py
rbac/util/config.py
rbac/util/current_date_time.py
rbac/util/date.py
rbac/util/day.py
rbac/util/fortress_error.py
rbac/util/global_ids.py
rbac/util/lockdate.py
rbac/util/logger.py
rbac/util/time.py
rbac/util/timeout.py
rbac/util/utils.py
rbac/util/validator.py
py_fortress-0.1.7.dist-info/LICENSE
py_fortress-0.1.7.dist-info/METADATA
py_fortress-0.1.7.dist-info/WHEEL
py_fortress-0.1.7.dist-info/entry_points.txt
py_fortress-0.1.7.dist-info/top_level.txt
py_fortress-0.1.7.dist-info/RECORD
