Metadata-Version: 2.1
Name: py-fortress
Version: 0.1.7
Summary: RBAC for Python 3
Home-page: https://github.com/shawnmckinney/py-fortress
Author: Symas Corporation
Author-email: smckinney@symas.com
License: Apache License 2.0
Keywords: authorization rbac security
Classifier: Development Status :: 4 - Beta
Classifier: Programming Language :: Python :: 3
Classifier: Intended Audience :: Developers
Classifier: License :: OSI Approved :: Apache Software License
Classifier: Topic :: Security
Classifier: Topic :: Software Development :: Libraries :: Application Frameworks
Classifier: Topic :: Software Development :: Libraries :: Python Modules
Requires-Python: >=3.6
License-File: LICENSE
Requires-Dist: python-ldap (>=3.4.2)
Requires-Dist: six (>=1.16.0)
Requires-Dist: ldappool (>=3.0.0)
